{
  "type": "GepPromptArtifact",
  "at": "2026-03-30T14:30:08.230Z",
  "cycle_id": "Cycle #0238",
  "run_id": "run_1774881007700",
  "prompt_path": "/root/.openclaw/workspace/workspace/memory/evolution/gep_prompt_Cycle_#0238_run_1774881007700.txt",
  "meta": {
    "agent": "main",
    "drift_enabled": false,
    "review_mode": false,
    "dry_run": false,
    "mutation_id": "mut_1774881007687",
    "personality_key": "rigor=0.7|creativity=0.3|verbosity=0.3|risk_tolerance=0.4|obedience=0.9"
  }
}
